{
  "id": 416,
  "name": "Vespiquen",
  "type1": "Bug",
  "type2": "Flying",
  "hp": 70,
  "attack": 80,
  "defense": 102,
  "sp_atk": 80,
  "sp_def": 102,
  "speed": 40,
  "total": 474,
  "abilities": [
    "Pressure",
    "Unnerve"
  ],
  "height": 1.2,
  "weight": 38.5,
  "gender_ratio": {},
  "evos": [],
  "prevo": "Combee",
  "evo_level": 21,
  "evo_type": null,
  "evo_item": null,
  "image_url": "https://play.pokemonshowdown.com/sprites/gen5ani/vespiquen.gif",
  "image_path": "D:\\baizhan_program\\my_pokedex\\Pok-dex\\backend\\spider\\pokemon_images\\416_vespiquen.gif"
}