{
  "id": 1023,
  "name": "ironcrown",
  "level_up": [
    "confusion",
    "electricterrain",
    "flashcannon",
    "futuresight",
    "hyperbeam",
    "irondefense",
    "leer",
    "metalburst",
    "metalclaw",
    "psychocut",
    "psyshock",
    "quickguard",
    "sacredsword",
    "slash",
    "smartstrike",
    "tachyoncutter",
    "voltswitch"
  ],
  "egg_moves": [],
  "tm_moves": [
    "agility",
    "airslash",
    "bodyslam",
    "brickbreak",
    "bulldoze",
    "calmmind",
    "doubleedge",
    "electricterrain",
    "endure",
    "expandingforce",
    "facade",
    "flashcannon",
    "focusblast",
    "futuresight",
    "gigaimpact",
    "gravity",
    "heavyslam",
    "hyperbeam",
    "irondefense",
    "ironhead",
    "metalclaw",
    "metalsound",
    "protect",
    "psychic",
    "psychicnoise",
    "psyshock",
    "rest",
    "scaryface",
    "sleeptalk",
    "smartstrike",
    "solarblade",
    "steelbeam",
    "storedpower",
    "substitute",
    "supercellslam",
    "swordsdance",
    "takedown",
    "terablast",
    "voltswitch",
    "xscissor",
    "zenheadbutt"
  ],
  "tutor_moves": []
}