{
  "id": 110,
  "name": "weezinggalar",
  "level_up": [
    "aromatherapy",
    "aromaticmist",
    "assurance",
    "belch",
    "clearsmog",
    "defog",
    "destinybond",
    "doublehit",
    "explosion",
    "fairywind",
    "haze",
    "heatwave",
    "memento",
    "mistyterrain",
    "poisongas",
    "selfdestruct",
    "sludge",
    "sludgebomb",
    "smog",
    "smokescreen",
    "strangesteam",
    "tackle",
    "toxic"
  ],
  "egg_moves": [],
  "tm_moves": [
    "acidspray",
    "assurance",
    "attract",
    "bodyslam",
    "brutalswing",
    "curse",
    "darkpulse",
    "dazzlinggleam",
    "doubleedge",
    "endure",
    "facade",
    "fireblast",
    "flamethrower",
    "gigaimpact",
    "gunkshot",
    "gyroball",
    "haze",
    "heatwave",
    "hyperbeam",
    "mistyexplosion",
    "mistyterrain",
    "overheat",
    "painsplit",
    "payback",
    "playrough",
    "protect",
    "psybeam",
    "raindance",
    "rest",
    "round",
    "scaryface",
    "screech",
    "selfdestruct",
    "shadowball",
    "sleeptalk",
    "sludgebomb",
    "sludgewave",
    "snore",
    "spite",
    "substitute",
    "sunnyday",
    "takedown",
    "taunt",
    "terablast",
    "thief",
    "thunder",
    "thunderbolt",
    "toxic",
    "toxicspikes",
    "uproar",
    "venomdrench",
    "venoshock",
    "willowisp",
    "wonderroom"
  ],
  "tutor_moves": [
    "corrosivegas",
    "mistyexplosion"
  ]
}