{
  "id": 222,
  "name": "corsolagalar",
  "level_up": [
    "ancientpower",
    "astonish",
    "curse",
    "disable",
    "grudge",
    "harden",
    "hex",
    "mirrorcoat",
    "nightshade",
    "powergem",
    "spite",
    "strengthsap",
    "tackle"
  ],
  "egg_moves": [
    "confuseray",
    "destinybond",
    "haze",
    "headsmash",
    "naturepower",
    "waterpulse"
  ],
  "tm_moves": [
    "amnesia",
    "attract",
    "blizzard",
    "bodyslam",
    "brine",
    "bulldoze",
    "calmmind",
    "dig",
    "earthpower",
    "earthquake",
    "endure",
    "facade",
    "gigadrain",
    "hail",
    "hex",
    "hydropump",
    "icebeam",
    "iciclespear",
    "icywind",
    "irondefense",
    "lightscreen",
    "liquidation",
    "powergem",
    "protect",
    "psychic",
    "raindance",
    "reflect",
    "rest",
    "rockblast",
    "rockslide",
    "rocktomb",
    "round",
    "safeguard",
    "sandstorm",
    "scald",
    "screech",
    "selfdestruct",
    "shadowball",
    "sleeptalk",
    "snore",
    "stealthrock",
    "stompingtantrum",
    "stoneedge",
    "substitute",
    "sunnyday",
    "surf",
    "throatchop",
    "whirlpool",
    "willowisp"
  ],
  "tutor_moves": [
    "meteorbeam"
  ]
}