{
  "id": 319,
  "name": "sharpedo",
  "level_up": [
    "agility",
    "aquajet",
    "assurance",
    "bite",
    "crunch",
    "feint",
    "focusenergy",
    "icefang",
    "leer",
    "liquidation",
    "nightslash",
    "poisonfang",
    "rage",
    "scaryface",
    "screech",
    "skullbash",
    "slash",
    "swagger",
    "takedown",
    "taunt"
  ],
  "egg_moves": [],
  "tm_moves": [
    "agility",
    "assurance",
    "attract",
    "avalanche",
    "blizzard",
    "bounce",
    "brine",
    "bulldoze",
    "captivate",
    "closecombat",
    "confide",
    "crunch",
    "darkpulse",
    "dive",
    "doubleteam",
    "earthquake",
    "endure",
    "facade",
    "focusenergy",
    "frustration",
    "gigaimpact",
    "hail",
    "hiddenpower",
    "hydropump",
    "hyperbeam",
    "icebeam",
    "icefang",
    "icywind",
    "liquidation",
    "naturalgift",
    "payback",
    "poisonjab",
    "protect",
    "psychicfangs",
    "raindance",
    "rest",
    "retaliate",
    "roar",
    "rocksmash",
    "rocktomb",
    "round",
    "scald",
    "scaryface",
    "screech",
    "secretpower",
    "sleeptalk",
    "snarl",
    "snore",
    "strength",
    "substitute",
    "surf",
    "swagger",
    "swift",
    "taunt",
    "thief",
    "torment",
    "toxic",
    "uproar",
    "waterfall",
    "waterpulse",
    "whirlpool",
    "zenheadbutt"
  ],
  "tutor_moves": [
    "ancientpower",
    "bounce",
    "darkpulse",
    "dive",
    "doubleedge",
    "endure",
    "flipturn",
    "furycutter",
    "icywind",
    "liquidation",
    "mimic",
    "mudslap",
    "scaleshot",
    "sleeptalk",
    "snore",
    "spite",
    "substitute",
    "superfang",
    "swagger",
    "swift",
    "uproar",
    "waterpulse",
    "zenheadbutt"
  ]
}