{
  "id": 330,
  "name": "flygon",
  "level_up": [
    "astonish",
    "bide",
    "bite",
    "boomburst",
    "bugbuzz",
    "bulldoze",
    "crunch",
    "dig",
    "dragonbreath",
    "dragonclaw",
    "dragondance",
    "dragonrush",
    "dragontail",
    "earthpower",
    "earthquake",
    "feint",
    "feintattack",
    "fissure",
    "hyperbeam",
    "laserfocus",
    "mudslap",
    "rockslide",
    "sandattack",
    "sandstorm",
    "sandtomb",
    "screech",
    "sonicboom",
    "superpower",
    "supersonic",
    "uproar"
  ],
  "egg_moves": [],
  "tm_moves": [
    "aerialace",
    "agility",
    "aircutter",
    "airslash",
    "alluringvoice",
    "attract",
    "bodyslam",
    "breakingswipe",
    "brutalswing",
    "bugbite",
    "bugbuzz",
    "bulldoze",
    "captivate",
    "confide",
    "crunch",
    "defog",
    "dig",
    "doubleedge",
    "doubleteam",
    "dracometeor",
    "dragoncheer",
    "dragonclaw",
    "dragondance",
    "dragonpulse",
    "dragontail",
    "dualwingbeat",
    "earthpower",
    "earthquake",
    "endure",
    "facade",
    "fireblast",
    "firepunch",
    "firespin",
    "flamethrower",
    "fly",
    "focusenergy",
    "frustration",
    "gigadrain",
    "gigaimpact",
    "heatwave",
    "helpinghand",
    "hiddenpower",
    "honeclaws",
    "hyperbeam",
    "incinerate",
    "irontail",
    "megakick",
    "megapunch",
    "mudshot",
    "mudslap",
    "naturalgift",
    "outrage",
    "poweruppunch",
    "protect",
    "psychicnoise",
    "rest",
    "rockslide",
    "rocksmash",
    "rocktomb",
    "roost",
    "round",
    "sandstorm",
    "sandtomb",
    "scaleshot",
    "scorchingsands",
    "screech",
    "secretpower",
    "silverwind",
    "sleeptalk",
    "snore",
    "solarbeam",
    "stealthrock",
    "steelwing",
    "stoneedge",
    "strength",
    "strugglebug",
    "substitute",
    "sunnyday",
    "superpower",
    "swagger",
    "swift",
    "tailwind",
    "takedown",
    "terablast",
    "throatchop",
    "thunderpunch",
    "toxic",
    "uproar",
    "uturn",
    "vacuumwave"
  ],
  "tutor_moves": [
    "aircutter",
    "bodyslam",
    "bugbite",
    "defog",
    "doubleedge",
    "dracometeor",
    "dragonpulse",
    "dualwingbeat",
    "earthpower",
    "endure",
    "firepunch",
    "furycutter",
    "gigadrain",
    "headbutt",
    "heatwave",
    "irontail",
    "laserfocus",
    "mimic",
    "mudslap",
    "ominouswind",
    "outrage",
    "rockslide",
    "roost",
    "scaleshot",
    "scorchingsands",
    "signalbeam",
    "sleeptalk",
    "snore",
    "substitute",
    "superpower",
    "swagger",
    "swift",
    "tailwind",
    "throatchop",
    "thunderpunch",
    "twister",
    "uproar"
  ]
}