{
  "id": 424,
  "name": "ambipom",
  "level_up": [
    "agility",
    "astonish",
    "batonpass",
    "doublehit",
    "dualchop",
    "fling",
    "furyswipes",
    "lastresort",
    "nastyplot",
    "sandattack",
    "scratch",
    "screech",
    "swift",
    "tailwhip",
    "tickle"
  ],
  "egg_moves": [],
  "tm_moves": [
    "acrobatics",
    "aerialace",
    "agility",
    "attract",
    "batonpass",
    "brickbreak",
    "captivate",
    "chillingwater",
    "confide",
    "cut",
    "dig",
    "doubleedge",
    "doubleteam",
    "dreameater",
    "endeavor",
    "endure",
    "facade",
    "firepunch",
    "fling",
    "focuspunch",
    "foulplay",
    "frustration",
    "gigaimpact",
    "grassknot",
    "gunkshot",
    "helpinghand",
    "hiddenpower",
    "honeclaws",
    "hyperbeam",
    "icepunch",
    "irontail",
    "knockoff",
    "lowkick",
    "lowsweep",
    "metronome",
    "mudshot",
    "mudslap",
    "nastyplot",
    "naturalgift",
    "payback",
    "poweruppunch",
    "protect",
    "raindance",
    "rest",
    "retaliate",
    "rocksmash",
    "round",
    "secretpower",
    "seedbomb",
    "shadowball",
    "shadowclaw",
    "shockwave",
    "sleeptalk",
    "smackdown",
    "snatch",
    "solarbeam",
    "spite",
    "strength",
    "substitute",
    "sunnyday",
    "swagger",
    "swift",
    "takedown",
    "taunt",
    "terablast",
    "thief",
    "throatchop",
    "thunder",
    "thunderbolt",
    "thunderpunch",
    "thunderwave",
    "toxic",
    "trailblaze",
    "tripleaxel",
    "upperhand",
    "uturn",
    "waterpulse",
    "workup"
  ],
  "tutor_moves": [
    "bounce",
    "covet",
    "firepunch",
    "focuspunch",
    "foulplay",
    "furycutter",
    "gunkshot",
    "headbutt",
    "icepunch",
    "irontail",
    "knockoff",
    "laserfocus",
    "lastresort",
    "lowkick",
    "mudslap",
    "roleplay",
    "seedbomb",
    "shockwave",
    "sleeptalk",
    "snatch",
    "snore",
    "spite",
    "swift",
    "thunderpunch",
    "uproar",
    "waterpulse"
  ]
}