{
  "id": 476,
  "name": "probopass",
  "level_up": [
    "block",
    "discharge",
    "earthpower",
    "gravity",
    "irondefense",
    "lockon",
    "magnetbomb",
    "magneticflux",
    "magnetrise",
    "powergem",
    "rest",
    "rockblast",
    "rockslide",
    "sandstorm",
    "spark",
    "stoneedge",
    "tackle",
    "thunderwave",
    "triattack",
    "wideguard",
    "zapcannon"
  ],
  "egg_moves": [],
  "tm_moves": [
    "attract",
    "bodypress",
    "bodyslam",
    "bulldoze",
    "captivate",
    "confide",
    "curse",
    "dazzlinggleam",
    "doubleedge",
    "doubleteam",
    "earthpower",
    "earthquake",
    "endure",
    "explosion",
    "facade",
    "firepunch",
    "flashcannon",
    "frustration",
    "gigaimpact",
    "gravity",
    "hardpress",
    "heavyslam",
    "helpinghand",
    "hiddenpower",
    "highhorsepower",
    "hyperbeam",
    "icepunch",
    "irondefense",
    "ironhead",
    "metalsound",
    "meteorbeam",
    "naturalgift",
    "painsplit",
    "powergem",
    "protect",
    "rest",
    "rockblast",
    "rockpolish",
    "rockslide",
    "rocksmash",
    "rocktomb",
    "round",
    "sandstorm",
    "sandtomb",
    "secretpower",
    "shockwave",
    "sleeptalk",
    "smackdown",
    "stealthrock",
    "steelbeam",
    "stompingtantrum",
    "stoneedge",
    "strength",
    "substitute",
    "sunnyday",
    "supercellslam",
    "swagger",
    "takedown",
    "taunt",
    "terablast",
    "thunder",
    "thunderbolt",
    "thunderpunch",
    "thunderwave",
    "torment",
    "toxic",
    "voltswitch"
  ],
  "tutor_moves": [
    "allyswitch",
    "ancientpower",
    "block",
    "earthpower",
    "firepunch",
    "gravity",
    "headbutt",
    "icepunch",
    "irondefense",
    "ironhead",
    "magiccoat",
    "magnetrise",
    "mudslap",
    "painsplit",
    "rollout",
    "shockwave",
    "sleeptalk",
    "snore",
    "stealthrock",
    "stompingtantrum",
    "telekinesis",
    "thunderpunch"
  ]
}