{
  "id": 889,
  "name": "zamazenta",
  "level_up": [
    "bite",
    "closecombat",
    "crunch",
    "gigaimpact",
    "howl",
    "irondefense",
    "ironhead",
    "laserfocus",
    "metalburst",
    "metalclaw",
    "moonblast",
    "quickattack",
    "slash",
    "wideguard"
  ],
  "egg_moves": [],
  "tm_moves": [
    "agility",
    "bodypress",
    "bodyslam",
    "brickbreak",
    "closecombat",
    "coaching",
    "crunch",
    "dazzlinggleam",
    "dig",
    "endure",
    "facade",
    "firefang",
    "flashcannon",
    "focusblast",
    "focusenergy",
    "gigaimpact",
    "guardswap",
    "heavyslam",
    "helpinghand",
    "hyperbeam",
    "hypervoice",
    "icefang",
    "imprison",
    "irondefense",
    "ironhead",
    "irontail",
    "lightscreen",
    "metalclaw",
    "payback",
    "playrough",
    "powerswap",
    "protect",
    "psychicfangs",
    "raindance",
    "reflect",
    "rest",
    "retaliate",
    "revenge",
    "reversal",
    "roar",
    "round",
    "safeguard",
    "sandstorm",
    "scaryface",
    "sleeptalk",
    "snarl",
    "snore",
    "solarbeam",
    "steelbeam",
    "stoneedge",
    "substitute",
    "sunnyday",
    "swift",
    "tailslap",
    "takedown",
    "terablast",
    "thunderfang",
    "trailblaze",
    "wildcharge",
    "workup"
  ],
  "tutor_moves": [
    "coaching",
    "steelbeam"
  ]
}