{
  "id": 901,
  "name": "ursaluna",
  "level_up": [
    "covet",
    "faketears",
    "furyswipes",
    "hammerarm",
    "headlongrush",
    "highhorsepower",
    "leer",
    "lick",
    "payback",
    "playnice",
    "playrough",
    "rest",
    "scaryface",
    "scratch",
    "slash",
    "snore",
    "sweetscent",
    "thrash"
  ],
  "egg_moves": [],
  "tm_moves": [
    "aerialace",
    "avalanche",
    "bodypress",
    "bodyslam",
    "brickbreak",
    "bulkup",
    "bulldoze",
    "charm",
    "closecombat",
    "crunch",
    "curse",
    "dig",
    "doubleedge",
    "drainpunch",
    "earthpower",
    "earthquake",
    "endure",
    "facade",
    "faketears",
    "firepunch",
    "fling",
    "focuspunch",
    "gigaimpact",
    "gunkshot",
    "hardpress",
    "heavyslam",
    "helpinghand",
    "highhorsepower",
    "hyperbeam",
    "hypervoice",
    "icepunch",
    "lowkick",
    "metalclaw",
    "metronome",
    "playrough",
    "protect",
    "raindance",
    "rest",
    "roar",
    "rockslide",
    "rocktomb",
    "scaryface",
    "seedbomb",
    "shadowclaw",
    "sleeptalk",
    "smackdown",
    "stompingtantrum",
    "stoneedge",
    "substitute",
    "sunnyday",
    "supercellslam",
    "swift",
    "swordsdance",
    "takedown",
    "taunt",
    "terablast",
    "thief",
    "throatchop",
    "thunderpunch",
    "trailblaze",
    "uproar"
  ],
  "tutor_moves": []
}