{
  "id": 913,
  "name": "quaxwell",
  "level_up": [
    "acrobatics",
    "airslash",
    "aquacutter",
    "aquajet",
    "doublehit",
    "featherdance",
    "focusenergy",
    "growl",
    "liquidation",
    "lowsweep",
    "pound",
    "watergun",
    "waterpulse",
    "wingattack",
    "workup"
  ],
  "egg_moves": [],
  "tm_moves": [
    "acrobatics",
    "aerialace",
    "aircutter",
    "airslash",
    "batonpass",
    "bravebird",
    "chillingwater",
    "disarmingvoice",
    "encore",
    "endure",
    "facade",
    "featherdance",
    "flipturn",
    "helpinghand",
    "hydropump",
    "liquidation",
    "lowkick",
    "lowsweep",
    "mistyterrain",
    "protect",
    "psychup",
    "raindance",
    "rest",
    "sleeptalk",
    "substitute",
    "surf",
    "swift",
    "takedown",
    "terablast",
    "tripleaxel",
    "waterpledge",
    "waterpulse",
    "whirlpool"
  ],
  "tutor_moves": []
}