{
  "id": 924,
  "name": "tandemaus",
  "level_up": [
    "babydolleyes",
    "beatup",
    "bulletseed",
    "charm",
    "copycat",
    "doublehit",
    "echoedvoice",
    "encore",
    "helpinghand",
    "hypervoice",
    "playrough",
    "populationbomb",
    "pound",
    "superfang"
  ],
  "egg_moves": [
    "afteryou",
    "batonpass",
    "bite",
    "feint",
    "switcheroo",
    "tickle"
  ],
  "tm_moves": [
    "aerialace",
    "agility",
    "batonpass",
    "bulletseed",
    "charm",
    "crunch",
    "dig",
    "doubleedge",
    "encore",
    "endure",
    "facade",
    "faketears",
    "grassknot",
    "helpinghand",
    "hypervoice",
    "lowkick",
    "lowsweep",
    "mudshot",
    "mudslap",
    "playrough",
    "protect",
    "raindance",
    "rest",
    "seedbomb",
    "shadowclaw",
    "sleeptalk",
    "substitute",
    "sunnyday",
    "superfang",
    "swift",
    "takedown",
    "taunt",
    "terablast",
    "thief",
    "thunderwave",
    "uturn",
    "waterpulse"
  ],
  "tutor_moves": []
}